{"v":"4.8.0","meta":{"g":"LottieFiles AE 1.0.0","a":"","k":"","d":"","tc":""},"fr":30,"ip":0,"op":781,"w":500,"h":300,"nm":"Mail success","ddd":1,"assets":[],"layers":[{"ddd":0,"ind":1,"ty":4,"nm":"Group 6908","sr":1,"ks":{"o":{"a":0,"k":100,"ix":11},"r":{"a":0,"k":0,"ix":10},"p":{"a":1,"k":[{"i":{"x":0.5,"y":1},"o":{"x":0.5,"y":0},"t":89,"s":[298.09,70.949,0],"to":[-8.015,13.175,0],"ti":[8.015,-13.175,0]},{"i":{"x":0,"y":0},"o":{"x":0.167,"y":0.167},"t":99,"s":[250,150,0],"to":[0,0,0],"ti":[0,0,0]},{"i":{"x":0,"y":0},"o":{"x":0.05,"y":0.05},"t":128,"s":[250,150,0],"to":[0,0,0],"ti":[0,0,0]},{"i":{"x":0,"y":1},"o":{"x":0.05,"y":0},"t":274,"s":[250,150,0],"to":[-0.549,-13.065,0],"ti":[0.549,13.065,0]},{"t":298,"s":[246.706,71.607,0]}],"ix":2},"a":{"a":0,"k":[-412.889,-487.431,0],"ix":1},"s":{"a":1,"k":[{"i":{"x":[0.67,0.67,0.67],"y":[1,1,1]},"o":{"x":[0.33,0.33,0.33],"y":[0,0,0]},"t":10,"s":[0,0,100]},{"i":{"x":[0.833,0.833,0.833],"y":[1,1,1]},"o":{"x":[0.167,0.167,0.167],"y":[0,0,0]},"t":32,"s":[100,100,100]},{"i":{"x":[0,0,0],"y":[1,1,1]},"o":{"x":[0.167,0.167,0.167],"y":[0,0,0]},"t":103,"s":[100,100,100]},{"i":{"x":[0,0,0],"y":[1,1,1]},"o":{"x":[0.05,0.05,0.05],"y":[0,0,0]},"t":128,"s":[209.777,209.777,100]},{"i":{"x":[0,0,0],"y":[1,1,1]},"o":{"x":[0.05,0.05,0.05],"y":[0,0,0]},"t":274,"s":[209.777,209.777,100]},{"t":298,"s":[100,100,100]}],"ix":6}},"ao":0,"shapes":[{"ty":"gr","it":[{"ind":0,"ty":"sh","ix":1,"ks":{"a":0,"k":{"i":[[-1.061,6.718],[-3.62,7.694],[-4.596,6.718],[-8.839,2.475],[-9.815000000000001,-0.08499999999999996],[-6.279,-2.037],[-2.828,1.414],[5.303,-6.718],[7.863,-7.694],[9.815000000000001,-4.1579999999999995]],"o":[[-2.037,7.694],[-4.596,6.718],[-4.596,6.718],[-9.815000000000001,1.499],[-7.863,-2.037],[-5.303,-1.061],[-2.828,1.414],[6.279,-7.694],[9.815000000000001,-5.742],[8.839,-3.182]],"v":[[-1.061,6.718],[-4.596,6.718],[-4.596,6.718],[-8.839,2.475],[-8.839,-1.061],[-5.303,-1.061],[-2.828,1.414],[5.303,-6.718],[8.839,-6.718],[8.839,-3.182]],"c":true},"ix":2},"nm":"Path 1","mn":"ADBE Vector Shape - Group","hd":false},{"ty":"fl","c":{"a":0,"k":[1,1,1],"ix":4},"o":{"a":0,"k":100,"ix":5},"r":1,"bm":0,"nm":"Fill 1","mn":"ADBE Vector Graphic - Fill","hd":false},{"ty":"tr","p":{"a":0,"k":[-415.183,-479.803],"ix":2},"a":{"a":0,"k":[-2.795,7.005],"ix":1},"s":{"a":1,"k":[{"i":{"x":[0.5,0.5],"y":[1,1]},"o":{"x":[0.5,0.5],"y":[0,0]},"t":23,"s":[0,0]},{"t":43,"s":[100,100]}],"ix":3},"r":{"a":0,"k":0,"ix":6},"o":{"a":0,"k":100,"ix":7},"sk":{"a":0,"k":0,"ix":4},"sa":{"a":0,"k":0,"ix":5},"nm":"Transform"}],"nm":"Union 163","np":2,"cix":2,"bm":0,"ix":1,"mn":"ADBE Vector Group","hd":false},{"ty":"gr","it":[{"ind":0,"ty":"sh","ix":1,"ks":{"a":0,"k":{"i":[[-10.493,-19],[19,-10.493],[10.493,19],[-19,10.493]],"o":[[10.493,-19],[19,10.493],[-10.493,19],[-19,-10.493]],"v":[[0,-19],[19,0],[0,19],[-19,0]],"c":true},"ix":2},"nm":"Path 1","mn":"ADBE Vector Shape - Group","hd":false},{"ty":"fl","c":{"a":0,"k":[0.1564,0.4701,0.7636,1],"ix":4},"o":{"a":0,"k":100,"ix":5},"r":1,"bm":0,"nm":"Fill 1","mn":"ADBE Vector Graphic - Fill","hd":false},{"ty":"tr","p":{"a":0,"k":[-412.889,-487.431],"ix":2},"a":{"a":0,"k":[0,0],"ix":1},"s":{"a":0,"k":[100,100],"ix":3},"r":{"a":0,"k":0,"ix":6},"o":{"a":0,"k":100,"ix":7},"sk":{"a":0,"k":0,"ix":4},"sa":{"a":0,"k":0,"ix":5},"nm":"Transform"}],"nm":"Ellipse 757","np":2,"cix":2,"bm":0,"ix":2,"mn":"ADBE Vector Group","hd":false}],"ip":89,"op":604,"st":10,"bm":0,"completed":true},{"ddd":0,"ind":2,"ty":4,"nm":"Path 2715","parent":6,"sr":1,"ks":{"o":{"a":1,"k":[{"i":{"x":[0.44],"y":[1]},"o":{"x":[0.56],"y":[0]},"t":36,"s":[0]},{"t":58,"s":[100]}],"ix":11},"r":{"a":0,"k":0,"ix":10},"p":{"a":0,"k":[24.879,-16.323,0],"ix":2},"a":{"a":0,"k":[-1.74,-1.004,0],"ix":1},"s":{"a":0,"k":[99.645,99.645,100],"ix":6}},"ao":0,"shapes":[{"ty":"gr","it":[{"ind":0,"ty":"sh","ix":1,"ks":{"a":0,"k":{"i":[[-39.4,-22.736],[-31.8,17.564],[39.4,22.736]],"o":[[-39.4,-22.736],[-31.8,17.564],[39.4,22.736]],"v":[[-39.4,-22.736],[-31.8,17.564],[39.4,22.736]],"c":true},"ix":2},"nm":"Path 1","mn":"ADBE Vector Shape - Group","hd":false},{"ty":"fl","c":{"a":0,"k":[0.9,0.9,0.9,1],"ix":4},"o":{"a":0,"k":100,"ix":5},"r":1,"bm":0,"nm":"Fill 1","mn":"ADBE Vector Graphic - Fill","hd":false},{"ty":"tr","p":{"a":0,"k":[0,0],"ix":2},"a":{"a":0,"k":[0,0],"ix":1},"s":{"a":0,"k":[100,100],"ix":3},"r":{"a":0,"k":0,"ix":6},"o":{"a":0,"k":100,"ix":7},"sk":{"a":0,"k":0,"ix":4},"sa":{"a":0,"k":0,"ix":5},"nm":"Transform"}],"nm":"Path 2715","np":2,"cix":2,"bm":0,"ix":1,"mn":"ADBE Vector Group","hd":false}],"ip":36,"op":593,"st":36,"bm":0,"completed":true},{"ddd":0,"ind":3,"ty":4,"nm":" 1705670607744-3","parent":4,"sr":1,"ks":{"o":{"a":0,"k":100,"ix":11},"r":{"a":0,"k":0,"ix":10},"p":{"a":0,"k":[220.442,-478.9,0],"ix":2},"a":{"a":0,"k":[137.731,-501.338,0],"ix":1},"s":{"a":0,"k":[100,100,100],"ix":6}},"ao":0,"shapes":[{"ty":"gr","it":[{"ind":0,"ty":"sh","ix":1,"ks":{"a":0,"k":{"i":[[-1.994,0.469],[1.345,-1.503],[2.0060000000000002,-1.607],[2.292,-0.663],[1.9909999999999999,-0.468],[-1.357,1.512],[-2.021,1.597],[-2.282,0.645]],"o":[[-1.994,0.469],[1.628,-1.686],[2.372,-1.0410000000000001],[2,-0.474],[1.982,-0.463],[-1.645,1.688],[-2.373,1.021],[-1.994,0.469]],"v":[[-1.994,0.469],[1.345,-1.503],[2.189,-1.324],[2.009,-0.48],[1.982,-0.463],[-1.357,1.512],[-2.197,1.309],[-1.994,0.469]],"c":true},"ix":2},"nm":"Path 1","mn":"ADBE Vector Shape - Group","hd":false},{"ty":"fl","c":{"a":0,"k":[0.24,0.6453,1,1],"ix":4},"o":{"a":0,"k":100,"ix":5},"r":1,"bm":0,"nm":"Fill 1","mn":"ADBE Vector Graphic - Fill","hd":false},{"ty":"tr","p":{"a":0,"k":[141.023,-498.564],"ix":2},"a":{"a":0,"k":[0,0],"ix":1},"s":{"a":0,"k":[100,100],"ix":3},"r":{"a":0,"k":0,"ix":6},"o":{"a":0,"k":100,"ix":7},"sk":{"a":0,"k":0,"ix":4},"sa":{"a":0,"k":0,"ix":5},"nm":"Transform"}],"nm":"Path 2712-2","np":2,"cix":2,"bm":0,"ix":1,"mn":"ADBE Vector Group","hd":false},{"ty":"gr","it":[{"ind":0,"ty":"sh","ix":1,"ks":{"a":0,"k":{"i":[[-2.1519999999999997,0.572],[1.506,-1.607],[2.1670000000000003,-1.7109999999999999],[2.453,-0.7669999999999999],[2.1519999999999997,-0.572],[-1.506,1.607],[-2.1670000000000003,1.7109999999999999],[-2.453,0.7669999999999999]],"o":[[-2.143,0.567],[1.789,-1.79],[2.533,-1.145],[2.161,-0.578],[2.143,-0.567],[-1.789,1.79],[-2.533,1.145],[-2.161,0.578]],"v":[[-2.143,0.567],[1.506,-1.607],[2.35,-1.428],[2.17,-0.584],[2.143,-0.567],[-1.506,1.607],[-2.35,1.428],[-2.17,0.584]],"c":true},"ix":2},"nm":"Path 1","mn":"ADBE Vector Shape - Group","hd":false},{"ty":"fl","c":{"a":0,"k":[0.24,0.6453,1,1],"ix":4},"o":{"a":0,"k":100,"ix":5},"r":1,"bm":0,"nm":"Fill 1","mn":"ADBE Vector Graphic - Fill","hd":false},{"ty":"tr","p":{"a":0,"k":[144.557,-496.873],"ix":2},"a":{"a":0,"k":[0,0],"ix":1},"s":{"a":0,"k":[100,100],"ix":3},"r":{"a":0,"k":0,"ix":6},"o":{"a":0,"k":100,"ix":7},"sk":{"a":0,"k":0,"ix":4},"sa":{"a":0,"k":0,"ix":5},"nm":"Transform"}],"nm":"Path 2711-2","np":2,"cix":2,"bm":0,"ix":2,"mn":"ADBE Vector Group","hd":false},{"ty":"gr","it":[{"ind":0,"ty":"sh","ix":1,"ks":{"a":0,"k":{"i":[[5.73,2.5],[-5.156,-3.572],[-5.821000000000001,-3.6199999999999997],[-6.027,-2.659],[5.156,3.572],[5.821000000000001,3.6199999999999997],[6.027,2.659]],"o":[[5.73,2.5],[-5.452,-3.731],[-6.139,-3.028],[-5.731,-2.5],[5.452,3.731],[6.139,3.028],[5.731,2.5]],"v":[[5.73,2.5],[-5.156,-3.572],[-5.98,-3.324],[-5.731,-2.5],[5.156,3.572],[5.98,3.324],[5.731,2.5]],"c":true},"ix":2},"nm":"Path 1","mn":"ADBE Vector Shape - Group","hd":false},{"ty":"fl","c":{"a":0,"k":[0.24,0.6453,1,1],"ix":4},"o":{"a":0,"k":100,"ix":5},"r":1,"bm":0,"nm":"Fill 1","mn":"ADBE Vector Graphic - Fill","hd":false},{"ty":"tr","p":{"a":0,"k":[140.862,-501.027],"ix":2},"a":{"a":0,"k":[0,0],"ix":1},"s":{"a":0,"k":[100,100],"ix":3},"r":{"a":0,"k":0,"ix":6},"o":{"a":0,"k":100,"ix":7},"sk":{"a":0,"k":0,"ix":4},"sa":{"a":0,"k":0,"ix":5},"nm":"Transform"}],"nm":"Path 2710-2","np":2,"cix":2,"bm":0,"ix":3,"mn":"ADBE Vector Group","hd":false},{"ty":"gr","it":[{"ind":0,"ty":"sh","ix":1,"ks":{"a":0,"k":{"i":[[2.4939999999999998,-1.329],[1.659,-1.5999999999999999],[0.6060000000000001,-1.38],[-2.019,0.221],[-2.475,0.581],[-2.492,1.3079999999999998],[-1.657,1.577],[-0.6040000000000001,1.359],[2.02,-0.244],[2.476,-0.604]],"o":[[1.9889999999999999,-1.556],[0.965,-1.501],[0.281,-1.192],[-2.279,0.352],[-2.608,1.082],[-1.986,1.5339999999999998],[-0.9630000000000001,1.48],[-0.28,1.169],[2.2800000000000002,-0.375],[2.609,-1.104]],"v":[[2.287,-1.423],[1.337,-1.549],[0.281,-1.192],[-2.019,0.221],[-2.563,0.858],[-2.283,1.402],[-1.336,1.526],[-0.28,1.169],[2.02,-0.244],[2.564,-0.881]],"c":true},"ix":2},"nm":"Path 1","mn":"ADBE Vector Shape - Group","hd":false},{"ind":1,"ty":"sh","ix":2,"ks":{"a":0,"k":{"i":[[1.293,1.588],[0.92,1.821],[-0.7080000000000001,2.564],[-3.15,2.686],[-4.654,1.637],[-3.848,-0.09100000000000003],[-0.928,-1.813],[0.7000000000000001,-2.557],[3.146,-2.691],[4.642,-1.63],[3.848,0.08999999999999997],[2.864,0.64],[1.296,1.603]],"o":[[1.293,1.588],[0.14800000000000002,2.273],[-2.365,2.79],[-4.37,2.1769999999999996],[-4.316,0.45100000000000007],[-3.231,-0.4],[-0.15700000000000003,-2.267],[2.357,-2.796],[4.356,-2.162],[4.313,-0.44899999999999995],[3.237,0.407],[2.864,0.64],[1.296,1.603]],"v":[[1.293,1.588],[0.92,1.821],[-1.596,2.677],[-3.863,2.377],[-4.531,1.106],[-3.231,-0.4],[-0.928,-1.813],[1.588,-2.667],[3.855,-2.367],[4.537,-1.099],[3.237,0.407],[2.864,0.64],[1.296,1.603]],"c":true},"ix":2},"nm":"Path 2","mn":"ADBE Vector Shape - Group","hd":false},{"ty":"fl","c":{"a":0,"k":[0.24,0.6453,1,1],"ix":4},"o":{"a":0,"k":100,"ix":5},"r":1,"bm":0,"nm":"Fill 1","mn":"ADBE Vector Graphic - Fill","hd":false},{"ty":"tr","p":{"a":0,"k":[133.015,-504.788],"ix":2},"a":{"a":0,"k":[0,0],"ix":1},"s":{"a":0,"k":[100,100],"ix":3},"r":{"a":0,"k":0,"ix":6},"o":{"a":0,"k":100,"ix":7},"sk":{"a":0,"k":0,"ix":4},"sa":{"a":0,"k":0,"ix":5},"nm":"Transform"}],"nm":"Path 2709-2","np":3,"cix":2,"bm":0,"ix":4,"mn":"ADBE Vector Group","hd":false}],"ip":298,"op":517,"st":298,"bm":0,"completed":true},{"ddd":0,"ind":4,"ty":4,"nm":"Group 8331","sr":1,"ks":{"o":{"a":0,"k":100,"ix":11},"r":{"a":0,"k":0,"ix":10},"p":{"a":0,"k":[252.282,197.505,0],"ix":2},"a":{"a":0,"k":[249.974,-438.144,0],"ix":1},"s":{"a":1,"k":[{"i":{"x":[0.5,0.5,0.5],"y":[1,1,1]},"o":{"x":[0.5,0.5,0.5],"y":[0,0,0]},"t":298,"s":[0,0,100]},{"t":318,"s":[100,100,100]}],"ix":6}},"ao":0,"shapes":[{"ty":"gr","it":[{"ty":"gr","it":[{"ty":"gr","it":[{"ty":"gr","it":[{"ind":0,"ty":"sh","ix":1,"ks":{"a":0,"k":{"i":[[-0.472,3.682],[0,3.682],[0.854,3.301],[0.854,-3.682],[0.472,-2.829],[0,-2.829],[-0.854,-3.21],[-0.854,2.829]],"o":[[0,3.682],[0.472,3.682],[0.854,2.829],[0.854,-3.21],[0,-2.829],[-0.472,-2.829],[-0.854,-3.682],[-0.854,3.301]],"v":[[0,3.682],[0,3.682],[0.854,2.829],[0.854,-3.682],[0,-2.829],[0,-2.829],[-0.854,-3.682],[-0.854,2.829]],"c":true},"ix":2},"nm":"Path 1","mn":"ADBE Vector Shape - Group","hd":false},{"ty":"fl","c":{"a":0,"k":[0.2339,0.5794,0.8261,1],"ix":4},"o":{"a":0,"k":100,"ix":5},"r":1,"bm":0,"nm":"Fill 1","mn":"ADBE Vector Graphic - Fill","hd":false},{"ty":"tr","p":{"a":0,"k":[246.357,-507.539],"ix":2},"a":{"a":0,"k":[0,0],"ix":1},"s":{"a":0,"k":[100,100],"ix":3},"r":{"a":0,"k":0,"ix":6},"o":{"a":0,"k":100,"ix":7},"sk":{"a":0,"k":0,"ix":4},"sa":{"a":0,"k":0,"ix":5},"nm":"Transform"}],"nm":"Path 2904","np":2,"cix":2,"bm":0,"ix":1,"mn":"ADBE Vector Group","hd":false},{"ty":"gr","it":[{"ind":0,"ty":"sh","ix":1,"ks":{"a":0,"k":{"i":[[-0.471,14.512],[0,14.512],[0.854,14.129999999999999],[0.854,-13.658],[0.472,-14.512],[0,-14.512],[-0.854,-14.129999999999999],[-0.854,13.658]],"o":[[0,14.512],[0.472,14.512],[0.854,13.658],[0.854,-14.129999999999999],[0,-14.512],[-0.472,-14.512],[-0.854,-13.658],[-0.853,14.129]],"v":[[0,14.512],[0,14.512],[0.854,13.658],[0.854,-13.658],[0,-14.512],[0,-14.512],[-0.854,-13.658],[-0.854,13.658]],"c":true},"ix":2},"nm":"Path 1","mn":"ADBE Vector Shape - Group","hd":false},{"ty":"fl","c":{"a":0,"k":[0.078,0.2661,0.442,1],"ix":4},"o":{"a":0,"k":100,"ix":5},"r":1,"bm":0,"nm":"Fill 1","mn":"ADBE Vector Graphic - Fill","hd":false},{"ty":"tr","p":{"a":0,"k":[246.357,-499.271],"ix":2},"a":{"a":0,"k":[0,0],"ix":1},"s":{"a":0,"k":[100,100],"ix":3},"r":{"a":0,"k":0,"ix":6},"o":{"a":0,"k":100,"ix":7},"sk":{"a":0,"k":0,"ix":4},"sa":{"a":0,"k":0,"ix":5},"nm":"Transform"}],"nm":"Path 2903","np":2,"cix":2,"bm":0,"ix":2,"mn":"ADBE Vector Group","hd":false},{"ty":"gr","it":[{"ind":0,"ty":"sh","ix":1,"ks":{"a":0,"k":{"i":[[-4.189,6],[4.188,1.161],[4.188,-6],[-4.189,-1.167]],"o":[[-4.189,6],[4.188,1.161],[4.188,-6],[-4.189,-1.167]],"v":[[-4.189,6],[4.188,1.161],[4.188,-6],[-4.189,-1.167]],"c":true},"ix":2},"nm":"Path 1","mn":"ADBE Vector Shape - Group","hd":false},{"ty":"fl","c":{"a":0,"k":[0.2818,0.6425,0.9582,1],"ix":4},"o":{"a":0,"k":100,"ix":5},"r":1,"bm":0,"nm":"Fill 1","mn":"ADBE Vector Graphic - Fill","hd":false},{"ty":"tr","p":{"a":0,"k":[250.464,-510.39],"ix":2},"a":{"a":0,"k":[0,0],"ix":1},"s":{"a":0,"k":[100,100],"ix":3},"r":{"a":0,"k":0,"ix":6},"o":{"a":0,"k":100,"ix":7},"sk":{"a":0,"k":0,"ix":4},"sa":{"a":0,"k":0,"ix":5},"nm":"Transform"}],"nm":"Path 2902","np":2,"cix":2,"bm":0,"ix":3,"mn":"ADBE Vector Group","hd":false},{"ty":"gr","it":[{"ind":0,"ty":"sh","ix":1,"ks":{"a":0,"k":{"i":[[-1.14,-1.7610000000000001],[1.813,-2.1870000000000003],[1.14,1.7610000000000001],[-1.813,2.1870000000000003]],"o":[[1,-2.923],[1.8279999999999998,0.512],[-1,2.923],[-1.8279999999999998,-0.512]],"v":[[0,-2.464],[1.813,-0.827],[0,2.464],[-1.813,0.827]],"c":true},"ix":2},"nm":"Path 1","mn":"ADBE Vector Shape - Group","hd":false},{"ty":"fl","c":{"a":0,"k":[0.078,0.2661,0.442,1],"ix":4},"o":{"a":0,"k":100,"ix":5},"r":1,"bm":0,"nm":"Fill 1","mn":"ADBE Vector Graphic - Fill","hd":false},{"ty":"tr","p":{"a":0,"k":[246.316,-485.35],"ix":2},"a":{"a":0,"k":[0,0],"ix":1},"s":{"a":0,"k":[100,100],"ix":3},"r":{"a":0,"k":0,"ix":6},"o":{"a":0,"k":100,"ix":7},"sk":{"a":0,"k":0,"ix":4},"sa":{"a":0,"k":0,"ix":5},"nm":"Transform"}],"nm":"Path 2901","np":2,"cix":2,"bm":0,"ix":4,"mn":"ADBE Vector Group","hd":false},{"ty":"gr","it":[{"ind":0,"ty":"sh","ix":1,"ks":{"a":0,"k":{"i":[[3.279,-4.577],[3.279,-4.577],[1.866,-4.8420000000000005],[-2.379,-0.6680000000000001],[-2.005,4.443],[-1.69,4.884],[-1.825,4.813000000000001],[-1.896,4.772],[-3.383,2.791],[-1.8010000000000002,-3.8],[2.362,-5.33]],"o":[[3.279,-4.577],[2.621,-4.868],[-0.76,-3.599],[-2.494,3.252],[-1.072,5.225],[-1.759,4.8500000000000005],[-1.89,4.772],[-2.8689999999999998,4.003],[-3.261,-1.0220000000000002],[1.079,-5.438],[3.267,-4.572]],"v":[[3.279,-4.577],[3.279,-4.577],[1.23,-4.506],[-2.379,2.04],[-1.072,5.225],[-1.69,4.884],[-1.89,4.772],[-1.896,4.772],[-3.261,1.557],[0.059,-4.843],[3.267,-4.572]],"c":true},"ix":2},"nm":"Path 1","mn":"ADBE Vector Shape - Group","hd":false},{"ty":"fl","c":{"a":0,"k":[0.078,0.2661,0.442,1],"ix":4},"o":{"a":0,"k":100,"ix":5},"r":1,"bm":0,"nm":"Fill 1","mn":"ADBE Vector Graphic - Fill","hd":false},{"ty":"tr","p":{"a":0,"k":[245.085,-485.745],"ix":2},"a":{"a":0,"k":[0,0],"ix":1},"s":{"a":0,"k":[100,100],"ix":3},"r":{"a":0,"k":0,"ix":6},"o":{"a":0,"k":100,"ix":7},"sk":{"a":0,"k":0,"ix":4},"sa":{"a":0,"k":0,"ix":5},"nm":"Transform"}],"nm":"Path 2900","np":2,"cix":2,"bm":0,"ix":5,"mn":"ADBE Vector Group","hd":false},{"ty":"gr","it":[{"ind":0,"ty":"sh","ix":1,"ks":{"a":0,"k":{"i":[[-2,-3.9949999999999997],[3.609,-4.353],[1.994,3.9939999999999998],[-3.609,4.348]],"o":[[1.99,-5.808],[3.609,1.0630000000000002],[-1.994,5.808],[-3.609,-1.0579999999999998]],"v":[[0,-4.901],[3.609,-1.645],[0,4.901],[-3.609,1.645]],"c":true},"ix":2},"nm":"Path 1","mn":"ADBE Vector Shape - Group","hd":false},{"ty":"fl","c":{"a":0,"k":[0.268,0.4044,0.532,1],"ix":4},"o":{"a":0,"k":100,"ix":5},"r":1,"bm":0,"nm":"Fill 1","mn":"ADBE Vector Graphic - Fill","hd":false},{"ty":"tr","p":{"a":0,"k":[246.317,-485.351],"ix":2},"a":{"a":0,"k":[0,0],"ix":1},"s":{"a":0,"k":[100,100],"ix":3},"r":{"a":0,"k":0,"ix":6},"o":{"a":0,"k":100,"ix":7},"sk":{"a":0,"k":0,"ix":4},"sa":{"a":0,"k":0,"ix":5},"nm":"Transform"}],"nm":"Path 2899","np":2,"cix":2,"bm":0,"ix":6,"mn":"ADBE Vector Group","hd":false},{"ty":"tr","p":{"a":0,"k":[246.317,-485.351],"ix":2},"a":{"a":0,"k":[246.317,-485.351],"ix":1},"s":{"a":0,"k":[100,100],"ix":3},"r":{"a":0,"k":0,"ix":6},"o":{"a":0,"k":100,"ix":7},"sk":{"a":0,"k":0,"ix":4},"sa":{"a":0,"k":0,"ix":5},"nm":"Transform"}],"nm":"Group 8330","np":6,"cix":2,"bm":0,"ix":1,"mn":"ADBE Vector Group","hd":false},{"ty":"gr","it":[{"ind":0,"ty":"sh","ix":1,"ks":{"a":0,"k":{"i":[[10.805,-29.506],[32.375,-23.006],[32.375,5.587],[-10.805,30.518],[-10.805,24.672],[-24.457,-9.128],[-32.375,-4.587],[10.795,-29.512],[10.805,-29.512]],"o":[[18.717,-34.068],[32.375,-0.259],[32.375,5.587],[-10.805,30.518],[-10.805,1.936],[-32.369,-4.581],[-32.375,-4.587],[10.795,-29.512],[10.805,-29.512]],"v":[[10.805,-29.506],[32.375,-0.259],[32.375,5.587],[-10.805,30.518],[-10.805,24.672],[-32.369,-4.581],[-32.375,-4.587],[10.795,-29.512],[10.805,-29.512]],"c":true},"ix":2},"nm":"Path 1","mn":"ADBE Vector Shape - Group","hd":false},{"ty":"fl","c":{"a":0,"k":[0.2867,0.4761,0.6533,1],"ix":4},"o":{"a":0,"k":100,"ix":5},"r":1,"bm":0,"nm":"Fill 1","mn":"ADBE Vector Graphic - Fill","hd":false},{"ty":"tr","p":{"a":0,"k":[249.137,-505.004],"ix":2},"a":{"a":0,"k":[0,0],"ix":1},"s":{"a":0,"k":[100,100],"ix":3},"r":{"a":0,"k":0,"ix":6},"o":{"a":0,"k":100,"ix":7},"sk":{"a":0,"k":0,"ix":4},"sa":{"a":0,"k":0,"ix":5},"nm":"Transform"}],"nm":"Path 2898","np":2,"cix":2,"bm":0,"ix":2,"mn":"ADBE Vector Group","hd":false},{"ty":"gr","it":[{"ty":"gr","it":[{"ty":"gr","it":[{"ind":0,"ty":"sh","ix":1,"ks":{"a":0,"k":{"i":[[-15.639,-5.081],[-3.082,5.081],[15.639,-5.081]],"o":[[-15.639,-5.081],[-3.082,5.081],[15.639,-5.081]],"v":[[-15.639,-5.081],[-3.082,5.081],[15.639,-5.081]],"c":true},"ix":2},"nm":"Path 1","mn":"ADBE Vector Shape - Group","hd":false},{"ty":"fl","c":{"a":0,"k":[0.851,0.8784,0.902,1],"ix":4},"o":{"a":0,"k":100,"ix":5},"r":1,"bm":0,"nm":"Fill 1","mn":"ADBE Vector Graphic - Fill","hd":false},{"ty":"tr","p":{"a":0,"k":[229.01,-489.822],"ix":2},"a":{"a":0,"k":[0,0],"ix":1},"s":{"a":0,"k":[100,100],"ix":3},"r":{"a":0,"k":0,"ix":6},"o":{"a":0,"k":100,"ix":7},"sk":{"a":0,"k":0,"ix":4},"sa":{"a":0,"k":0,"ix":5},"nm":"Transform"}],"nm":"Path 2897","np":2,"cix":2,"bm":0,"ix":1,"mn":"ADBE Vector Group","hd":false},{"ty":"gr","it":[{"ind":0,"ty":"sh","ix":1,"ks":{"a":0,"k":{"i":[[-10.429,-9.025],[-20.849,9.025],[10.429,9.025],[20.849,-9.025]],"o":[[-10.429,-9.025],[-20.849,9.025],[10.429,9.025],[20.849,-9.025]],"v":[[-10.429,-9.025],[-20.849,9.025],[10.429,9.025],[20.849,-9.025]],"c":true},"ix":2},"nm":"Path 1","mn":"ADBE Vector Shape - Group","hd":false},{"ty":"fl","c":{"a":0,"k":[0.9857,0.9903,0.9943,1],"ix":4},"o":{"a":0,"k":100,"ix":5},"r":1,"bm":0,"nm":"Fill 1","mn":"ADBE Vector Graphic - Fill","hd":false},{"ty":"tr","p":{"a":0,"k":[223.8,-485.877],"ix":2},"a":{"a":0,"k":[0,0],"ix":1},"s":{"a":0,"k":[100,100],"ix":3},"r":{"a":0,"k":0,"ix":6},"o":{"a":0,"k":100,"ix":7},"sk":{"a":0,"k":0,"ix":4},"sa":{"a":0,"k":0,"ix":5},"nm":"Transform"}],"nm":"Path 2896","np":2,"cix":2,"bm":0,"ix":2,"mn":"ADBE Vector Group","hd":false},{"ty":"tr","p":{"a":0,"k":[252.619,-511.512],"ix":2},"a":{"a":0,"k":[223.8,-485.877],"ix":1},"s":{"a":0,"k":[219.446,336.824],"ix":3},"r":{"a":0,"k":0,"ix":6},"o":{"a":0,"k":100,"ix":7},"sk":{"a":0,"k":0,"ix":4},"sa":{"a":0,"k":0,"ix":5},"nm":"Transform"}],"nm":"Group 8328","np":2,"cix":2,"bm":0,"ix":1,"mn":"ADBE Vector Group","hd":false},{"ty":"tr","p":{"a":0,"k":[108.781,-335.922],"ix":2},"a":{"a":0,"k":[0,0],"ix":1},"s":{"a":0,"k":[46.937,29.223],"ix":3},"r":{"a":0,"k":0,"ix":6},"o":{"a":0,"k":100,"ix":7},"sk":{"a":0,"k":0,"ix":4},"sa":{"a":0,"k":0,"ix":5},"nm":"Transform"}],"nm":"Group 8329","np":1,"cix":2,"bm":0,"ix":3,"mn":"ADBE Vector Group","hd":false},{"ty":"gr","it":[{"ind":0,"ty":"sh","ix":1,"ks":{"a":0,"k":{"i":[[-11.656,-9.346],[-12.145000000000001,22.19],[20.593,3.287],[-6.476,-12.337],[-11.662,-9.337]],"o":[[-33.344,3.286999999999999],[15.53,6.213],[20.593,3.287],[-6.476,-12.337],[-11.662,-9.337]],"v":[[-11.656,-9.346],[15.53,6.213],[20.593,3.287],[-6.476,-12.337],[-11.662,-9.337]],"c":true},"ix":2},"nm":"Path 1","mn":"ADBE Vector Shape - Group","hd":false},{"ty":"fl","c":{"a":0,"k":[0.268,0.4044,0.532,1],"ix":4},"o":{"a":0,"k":100,"ix":5},"r":1,"bm":0,"nm":"Fill 1","mn":"ADBE Vector Graphic - Fill","hd":false},{"ty":"tr","p":{"a":0,"k":[217.741,-477.768],"ix":2},"a":{"a":0,"k":[0,0],"ix":1},"s":{"a":0,"k":[100,100],"ix":3},"r":{"a":0,"k":0,"ix":6},"o":{"a":0,"k":100,"ix":7},"sk":{"a":0,"k":0,"ix":4},"sa":{"a":0,"k":0,"ix":5},"nm":"Transform"}],"nm":"Path 2895","np":2,"cix":2,"bm":0,"ix":4,"mn":"ADBE Vector Group","hd":false},{"ty":"gr","it":[{"ind":0,"ty":"sh","ix":1,"ks":{"a":0,"k":{"i":[[7.798,-13.97],[13.531,-1.3699999999999992],[13.531,13.97],[-13.531,-1.654],[7.803,-13.97]],"o":[[11.148,-8.831],[13.531,8.124],[13.531,13.97],[-13.531,-1.654],[7.803,-13.97]],"v":[[7.798,-13.97],[13.531,8.124],[13.531,13.97],[-13.531,-1.654],[7.803,-13.97]],"c":true},"ix":2},"nm":"Path 1","mn":"ADBE Vector Shape - Group","hd":false},{"ty":"fl","c":{"a":0,"k":[0.078,0.2661,0.442,1],"ix":4},"o":{"a":0,"k":100,"ix":5},"r":1,"bm":0,"nm":"Fill 1","mn":"ADBE Vector Graphic - Fill","hd":false},{"ty":"tr","p":{"a":0,"k":[224.802,-488.456],"ix":2},"a":{"a":0,"k":[0,0],"ix":1},"s":{"a":0,"k":[100,100],"ix":3},"r":{"a":0,"k":0,"ix":6},"o":{"a":0,"k":100,"ix":7},"sk":{"a":0,"k":0,"ix":4},"sa":{"a":0,"k":0,"ix":5},"nm":"Transform"}],"nm":"Path 2894","np":2,"cix":2,"bm":0,"ix":5,"mn":"ADBE Vector Group","hd":false},{"ty":"gr","it":[{"ind":0,"ty":"sh","ix":1,"ks":{"a":0,"k":{"i":[[-13.535,-3.416],[13.535,-19.805],[13.535,18.054],[-13.535,2.43]],"o":[[-13.535,-28.683],[13.535,12.208],[13.535,18.054],[-13.535,2.43]],"v":[[-13.535,-3.416],[13.535,12.208],[13.535,18.054],[-13.535,2.43]],"c":true},"ix":2},"nm":"Path 1","mn":"ADBE Vector Shape - Group","hd":false},{"ty":"fl","c":{"a":0,"k":[0.0314,0.3412,0.6275,1],"ix":4},"o":{"a":0,"k":100,"ix":5},"r":1,"bm":0,"nm":"Fill 1","mn":"ADBE Vector Graphic - Fill","hd":false},{"ty":"tr","p":{"a":0,"k":[224.805,-492.54],"ix":2},"a":{"a":0,"k":[0,0],"ix":1},"s":{"a":0,"k":[100,100],"ix":3},"r":{"a":0,"k":0,"ix":6},"o":{"a":0,"k":100,"ix":7},"sk":{"a":0,"k":0,"ix":4},"sa":{"a":0,"k":0,"ix":5},"nm":"Transform"}],"nm":"Path 2893","np":2,"cix":2,"bm":0,"ix":6,"mn":"ADBE Vector Group","hd":false},{"ty":"gr","it":[{"ind":0,"ty":"sh","ix":1,"ks":{"a":0,"k":{"i":[[0.003,-27.483],[-3.593,-25.869],[-3.597,23.737],[-2.134,27.399],[3.516,26.017000000000003],[3.601,23.834999999999997],[3.597,-23.883],[1.983,-27.479]],"o":[[-1.983,-27.479],[-3.597,-23.883],[-3.678,25.723999999999997],[1.84,27.561],[3.601,23.932000000000002],[3.597,23.737],[3.593,-25.869],[-0.003,-27.483]],"v":[[0.003,-27.483],[-3.597,-23.883],[-3.597,23.737],[-0.147,27.48],[3.597,24.03],[3.597,23.737],[3.597,-23.883],[-0.003,-27.483]],"c":true},"ix":2},"nm":"Path 1","mn":"ADBE Vector Shape - Group","hd":false},{"ty":"fl","c":{"a":0,"k":[0.078,0.2661,0.442,1],"ix":4},"o":{"a":0,"k":100,"ix":5},"r":1,"bm":0,"nm":"Fill 1","mn":"ADBE Vector Graphic - Fill","hd":false},{"ty":"tr","p":{"a":0,"k":[249.138,-464.417],"ix":2},"a":{"a":0,"k":[0,0],"ix":1},"s":{"a":0,"k":[100,100],"ix":3},"r":{"a":0,"k":0,"ix":6},"o":{"a":0,"k":100,"ix":7},"sk":{"a":0,"k":0,"ix":4},"sa":{"a":0,"k":0,"ix":5},"nm":"Transform"}],"nm":"Path 2892","np":2,"cix":2,"bm":0,"ix":7,"mn":"ADBE Vector Group","hd":false},{"ty":"gr","it":[{"ind":0,"ty":"sh","ix":1,"ks":{"a":0,"k":{"i":[[-9.591,-6.252],[17.361,-3.452],[9.59,6.252],[-17.361,3.452]],"o":[[9.584,-6.252],[17.361,3.452],[-9.59,6.252],[-17.361,-3.452]],"v":[[0,-6.252],[17.361,0],[0,6.252],[-17.361,0]],"c":true},"ix":2},"nm":"Path 1","mn":"ADBE Vector Shape - Group","hd":false},{"ty":"fl","c":{"a":0,"k":[0.1255,0.1529,0.1725,1],"ix":4},"o":{"a":0,"k":100,"ix":5},"r":1,"bm":0,"nm":"Fill 1","mn":"ADBE Vector Graphic - Fill","hd":false},{"ty":"tr","p":{"a":0,"k":[249.141,-438.045],"ix":2},"a":{"a":0,"k":[0,0],"ix":1},"s":{"a":0,"k":[100,100],"ix":3},"r":{"a":0,"k":0,"ix":6},"o":{"a":0,"k":20,"ix":7},"sk":{"a":0,"k":0,"ix":4},"sa":{"a":0,"k":0,"ix":5},"nm":"Transform"}],"nm":"Path 2891","np":2,"cix":2,"bm":0,"ix":8,"mn":"ADBE Vector Group","hd":false},{"ty":"tr","p":{"a":0,"k":[249.141,-438.045],"ix":2},"a":{"a":0,"k":[249.141,-438.045],"ix":1},"s":{"a":0,"k":[100,100],"ix":3},"r":{"a":0,"k":0,"ix":6},"o":{"a":0,"k":100,"ix":7},"sk":{"a":0,"k":0,"ix":4},"sa":{"a":0,"k":0,"ix":5},"nm":"Transform"}],"nm":" 1877935415520","np":8,"cix":2,"bm":0,"ix":1,"mn":"ADBE Vector Group","hd":false},{"ty":"tr","p":{"a":0,"k":[249.141,-438.045],"ix":2},"a":{"a":0,"k":[249.141,-438.045],"ix":1},"s":{"a":0,"k":[100,100],"ix":3},"r":{"a":0,"k":0,"ix":6},"o":{"a":0,"k":100,"ix":7},"sk":{"a":0,"k":0,"ix":4},"sa":{"a":0,"k":0,"ix":5},"nm":"Transform"}],"nm":"Layer_1-2","np":1,"cix":2,"bm":0,"ix":2,"mn":"ADBE Vector Group","hd":false}],"ip":298,"op":781,"st":298,"bm":0,"completed":true},{"ddd":0,"ind":5,"ty":4,"nm":"Group 6907","sr":1,"ks":{"o":{"a":0,"k":100,"ix":11},"r":{"a":0,"k":0,"ix":10},"p":{"a":0,"k":[248.682,132.872,0],"ix":2},"a":{"a":0,"k":[-462.296,-425.507,0],"ix":1},"s":{"a":1,"k":[{"i":{"x":[0.67,0.67,0.67],"y":[1,1,1]},"o":{"x":[0.33,0.33,0.33],"y":[0,0,0]},"t":56,"s":[0,0,100]},{"t":78,"s":[100,100,100]}],"ix":6}},"ao":0,"shapes":[{"ty":"gr","it":[{"ind":0,"ty":"sh","ix":1,"ks":{"a":0,"k":{"i":[[-1.061,6.718],[-3.62,7.694],[-4.596,6.718],[-8.839,2.475],[-9.815000000000001,-0.08499999999999996],[-6.279,-2.037],[-2.828,1.414],[5.303,-6.718],[7.863,-7.694],[9.815000000000001,-4.1579999999999995]],"o":[[-2.037,7.694],[-4.596,6.718],[-4.596,6.718],[-9.815000000000001,1.499],[-7.863,-2.037],[-5.303,-1.061],[-2.828,1.414],[6.279,-7.694],[9.815000000000001,-5.742],[8.839,-3.182]],"v":[[-1.061,6.718],[-4.596,6.718],[-4.596,6.718],[-8.839,2.475],[-8.839,-1.061],[-5.303,-1.061],[-2.828,1.414],[5.303,-6.718],[8.839,-6.718],[8.839,-3.182]],"c":true},"ix":2},"nm":"Path 1","mn":"ADBE Vector Shape - Group","hd":false},{"ty":"fl","c":{"a":0,"k":[1,1,1],"ix":4},"o":{"a":0,"k":100,"ix":5},"r":1,"bm":0,"nm":"Fill 1","mn":"ADBE Vector Graphic - Fill","hd":false},{"ty":"tr","p":{"a":0,"k":[-415.183,-479.803],"ix":2},"a":{"a":0,"k":[-2.795,7.005],"ix":1},"s":{"a":1,"k":[{"i":{"x":[0.5,0.5],"y":[1,1]},"o":{"x":[0.5,0.5],"y":[0,0]},"t":69,"s":[0,0]},{"t":89,"s":[100,100]}],"ix":3},"r":{"a":0,"k":0,"ix":6},"o":{"a":0,"k":100,"ix":7},"sk":{"a":0,"k":0,"ix":4},"sa":{"a":0,"k":0,"ix":5},"nm":"Transform"}],"nm":"Union 163","np":2,"cix":2,"bm":0,"ix":1,"mn":"ADBE Vector Group","hd":false},{"ty":"gr","it":[{"ind":0,"ty":"sh","ix":1,"ks":{"a":0,"k":{"i":[[-10.493,-19],[19,-10.493],[10.493,19],[-19,10.493]],"o":[[10.493,-19],[19,10.493],[-10.493,19],[-19,-10.493]],"v":[[0,-19],[19,0],[0,19],[-19,0]],"c":true},"ix":2},"nm":"Path 1","mn":"ADBE Vector Shape - Group","hd":false},{"ty":"fl","c":{"a":0,"k":[0.1564,0.4701,0.7636,1],"ix":4},"o":{"a":0,"k":100,"ix":5},"r":1,"bm":0,"nm":"Fill 1","mn":"ADBE Vector Graphic - Fill","hd":false},{"ty":"tr","p":{"a":0,"k":[-412.889,-487.431],"ix":2},"a":{"a":0,"k":[0,0],"ix":1},"s":{"a":0,"k":[100,100],"ix":3},"r":{"a":0,"k":0,"ix":6},"o":{"a":0,"k":100,"ix":7},"sk":{"a":0,"k":0,"ix":4},"sa":{"a":0,"k":0,"ix":5},"nm":"Transform"}],"nm":"Ellipse 757","np":2,"cix":2,"bm":0,"ix":2,"mn":"ADBE Vector Group","hd":false}],"ip":50,"op":90,"st":56,"bm":0,"completed":true},{"ddd":1,"ind":6,"ty":4,"nm":"Path 2713","sr":1,"ks":{"o":{"a":1,"k":[{"i":{"x":[0.43],"y":[1]},"o":{"x":[0.57],"y":[0]},"t":6,"s":[0]},{"i":{"x":[0.833],"y":[1]},"o":{"x":[0.57],"y":[0]},"t":22,"s":[100]},{"i":{"x":[0.833],"y":[1]},"o":{"x":[0.167],"y":[0]},"t":94,"s":[100]},{"t":111,"s":[0]}],"ix":11},"rx":{"a":0,"k":0,"ix":8},"ry":{"a":0,"k":0,"ix":9},"rz":{"a":0,"k":0,"ix":10},"or":{"a":0,"k":[0,0,0],"ix":7},"p":{"a":1,"k":[{"i":{"x":0.43,"y":1},"o":{"x":0.57,"y":0},"t":0,"s":[-94,343,0],"to":[57.333,-32.167,0],"ti":[-57.333,32.167,0]},{"i":{"x":0.95,"y":0.95},"o":{"x":0.57,"y":0.57},"t":22,"s":[250,150,0],"to":null,"ti":null},{"i":{"x":0.95,"y":1},"o":{"x":1,"y":0},"t":54,"s":[250,150,0],"to":null,"ti":null},{"i":{"x":0.95,"y":0.95},"o":{"x":0.167,"y":0.167},"t":71,"s":[250,135,0],"to":null,"ti":null},{"i":{"x":0.95,"y":1},"o":{"x":0.167,"y":0},"t":94,"s":[250,135,0],"to":[60.333,-34.167,0],"ti":[-60.333,34.167,0]},{"t":116,"s":[612,-70,0]}],"ix":2},"a":{"a":0,"k":[0,0,0],"ix":1},"s":{"a":0,"k":[124,124,124],"ix":6}},"ao":0,"shapes":[{"ty":"gr","it":[{"ind":0,"ty":"sh","ix":1,"ks":{"a":0,"k":{"i":[[-13.15,-37.905],[-65.65,-7.595],[13.15,37.905],[65.65,7.572]],"o":[[-13.15,-37.905],[-65.65,-7.595],[13.15,37.905],[65.65,7.572]],"v":[[-13.15,-37.905],[-65.65,-7.595],[13.15,37.905],[65.65,7.572]],"c":true},"ix":2},"nm":"Path 1","mn":"ADBE Vector Shape - Group","hd":false,"_render":true},{"ty":"fl","c":{"a":0,"k":[0.9857,0.9903,0.9943,1],"ix":4},"o":{"a":0,"k":100,"ix":5},"r":1,"bm":0,"nm":"Fill 1","mn":"ADBE Vector Graphic - Fill","hd":false,"_render":true},{"ty":"tr","p":{"a":0,"k":[0,0],"ix":2},"a":{"a":0,"k":[0,0],"ix":1},"s":{"a":0,"k":[100,100],"ix":3},"r":{"a":0,"k":0,"ix":6},"o":{"a":0,"k":100,"ix":7},"sk":{"a":0,"k":0,"ix":4},"sa":{"a":0,"k":0,"ix":5},"nm":"Transform","_render":true}],"nm":"Path 2713","np":2,"cix":2,"bm":0,"ix":1,"mn":"ADBE Vector Group","hd":false,"_render":true}],"ip":0,"op":604,"st":0,"bm":0,"completed":true},{"ddd":0,"ind":7,"ty":4,"nm":" 1705670607744-2","sr":1,"ks":{"o":{"a":1,"k":[{"i":{"x":[0.366],"y":[1]},"o":{"x":[0.395],"y":[0]},"t":23,"s":[100]},{"t":42,"s":[100]}],"ix":11},"r":{"a":0,"k":0,"ix":10},"p":{"a":1,"k":[{"i":{"x":0.42,"y":1},"o":{"x":0.58,"y":0},"t":6,"s":[552.847,-55.473,0],"to":[-51.167,33.5,0],"ti":[51.167,-33.5,0]},{"t":42,"s":[245.847,145.527,0]}],"ix":2},"a":{"a":0,"k":[137.731,-501.338,0],"ix":1},"s":{"a":0,"k":[260.044,260.044,100],"ix":6}},"ao":0,"shapes":[{"ty":"gr","it":[{"ind":0,"ty":"sh","ix":1,"ks":{"a":0,"k":{"i":[[-1.994,0.469],[1.345,-1.503],[2.0060000000000002,-1.607],[2.292,-0.663],[1.9909999999999999,-0.468],[-1.357,1.512],[-2.021,1.597],[-2.282,0.645]],"o":[[-1.994,0.469],[1.628,-1.686],[2.372,-1.0410000000000001],[2,-0.474],[1.982,-0.463],[-1.645,1.688],[-2.373,1.021],[-1.994,0.469]],"v":[[-1.994,0.469],[1.345,-1.503],[2.189,-1.324],[2.009,-0.48],[1.982,-0.463],[-1.357,1.512],[-2.197,1.309],[-1.994,0.469]],"c":true},"ix":2},"nm":"Path 1","mn":"ADBE Vector Shape - Group","hd":false},{"ty":"fl","c":{"a":0,"k":[0.24,0.6453,1,1],"ix":4},"o":{"a":0,"k":100,"ix":5},"r":1,"bm":0,"nm":"Fill 1","mn":"ADBE Vector Graphic - Fill","hd":false},{"ty":"tr","p":{"a":0,"k":[141.023,-498.564],"ix":2},"a":{"a":0,"k":[0,0],"ix":1},"s":{"a":0,"k":[100,100],"ix":3},"r":{"a":0,"k":0,"ix":6},"o":{"a":0,"k":100,"ix":7},"sk":{"a":0,"k":0,"ix":4},"sa":{"a":0,"k":0,"ix":5},"nm":"Transform"}],"nm":"Path 2712-2","np":2,"cix":2,"bm":0,"ix":1,"mn":"ADBE Vector Group","hd":false},{"ty":"gr","it":[{"ind":0,"ty":"sh","ix":1,"ks":{"a":0,"k":{"i":[[-2.1519999999999997,0.572],[1.506,-1.607],[2.1670000000000003,-1.7109999999999999],[2.453,-0.7669999999999999],[2.1519999999999997,-0.572],[-1.506,1.607],[-2.1670000000000003,1.7109999999999999],[-2.453,0.7669999999999999]],"o":[[-2.143,0.567],[1.789,-1.79],[2.533,-1.145],[2.161,-0.578],[2.143,-0.567],[-1.789,1.79],[-2.533,1.145],[-2.161,0.578]],"v":[[-2.143,0.567],[1.506,-1.607],[2.35,-1.428],[2.17,-0.584],[2.143,-0.567],[-1.506,1.607],[-2.35,1.428],[-2.17,0.584]],"c":true},"ix":2},"nm":"Path 1","mn":"ADBE Vector Shape - Group","hd":false},{"ty":"fl","c":{"a":0,"k":[0.24,0.6453,1,1],"ix":4},"o":{"a":0,"k":100,"ix":5},"r":1,"bm":0,"nm":"Fill 1","mn":"ADBE Vector Graphic - Fill","hd":false},{"ty":"tr","p":{"a":0,"k":[144.557,-496.873],"ix":2},"a":{"a":0,"k":[0,0],"ix":1},"s":{"a":0,"k":[100,100],"ix":3},"r":{"a":0,"k":0,"ix":6},"o":{"a":0,"k":100,"ix":7},"sk":{"a":0,"k":0,"ix":4},"sa":{"a":0,"k":0,"ix":5},"nm":"Transform"}],"nm":"Path 2711-2","np":2,"cix":2,"bm":0,"ix":2,"mn":"ADBE Vector Group","hd":false},{"ty":"gr","it":[{"ind":0,"ty":"sh","ix":1,"ks":{"a":0,"k":{"i":[[5.73,2.5],[-5.156,-3.572],[-5.821000000000001,-3.6199999999999997],[-6.027,-2.659],[5.156,3.572],[5.821000000000001,3.6199999999999997],[6.027,2.659]],"o":[[5.73,2.5],[-5.452,-3.731],[-6.139,-3.028],[-5.731,-2.5],[5.452,3.731],[6.139,3.028],[5.731,2.5]],"v":[[5.73,2.5],[-5.156,-3.572],[-5.98,-3.324],[-5.731,-2.5],[5.156,3.572],[5.98,3.324],[5.731,2.5]],"c":true},"ix":2},"nm":"Path 1","mn":"ADBE Vector Shape - Group","hd":false},{"ty":"fl","c":{"a":0,"k":[0.24,0.6453,1,1],"ix":4},"o":{"a":0,"k":100,"ix":5},"r":1,"bm":0,"nm":"Fill 1","mn":"ADBE Vector Graphic - Fill","hd":false},{"ty":"tr","p":{"a":0,"k":[140.862,-501.027],"ix":2},"a":{"a":0,"k":[0,0],"ix":1},"s":{"a":0,"k":[100,100],"ix":3},"r":{"a":0,"k":0,"ix":6},"o":{"a":0,"k":100,"ix":7},"sk":{"a":0,"k":0,"ix":4},"sa":{"a":0,"k":0,"ix":5},"nm":"Transform"}],"nm":"Path 2710-2","np":2,"cix":2,"bm":0,"ix":3,"mn":"ADBE Vector Group","hd":false},{"ty":"gr","it":[{"ind":0,"ty":"sh","ix":1,"ks":{"a":0,"k":{"i":[[2.4939999999999998,-1.329],[1.659,-1.5999999999999999],[0.6060000000000001,-1.38],[-2.019,0.221],[-2.475,0.581],[-2.492,1.3079999999999998],[-1.657,1.577],[-0.6040000000000001,1.359],[2.02,-0.244],[2.476,-0.604]],"o":[[1.9889999999999999,-1.556],[0.965,-1.501],[0.281,-1.192],[-2.279,0.352],[-2.608,1.082],[-1.986,1.5339999999999998],[-0.9630000000000001,1.48],[-0.28,1.169],[2.2800000000000002,-0.375],[2.609,-1.104]],"v":[[2.287,-1.423],[1.337,-1.549],[0.281,-1.192],[-2.019,0.221],[-2.563,0.858],[-2.283,1.402],[-1.336,1.526],[-0.28,1.169],[2.02,-0.244],[2.564,-0.881]],"c":true},"ix":2},"nm":"Path 1","mn":"ADBE Vector Shape - Group","hd":false},{"ind":1,"ty":"sh","ix":2,"ks":{"a":0,"k":{"i":[[1.293,1.588],[0.92,1.821],[-0.7080000000000001,2.564],[-3.15,2.686],[-4.654,1.637],[-3.848,-0.09100000000000003],[-0.928,-1.813],[0.7000000000000001,-2.557],[3.146,-2.691],[4.642,-1.63],[3.848,0.08999999999999997],[2.864,0.64],[1.296,1.603]],"o":[[1.293,1.588],[0.14800000000000002,2.273],[-2.365,2.79],[-4.37,2.1769999999999996],[-4.316,0.45100000000000007],[-3.231,-0.4],[-0.15700000000000003,-2.267],[2.357,-2.796],[4.356,-2.162],[4.313,-0.44899999999999995],[3.237,0.407],[2.864,0.64],[1.296,1.603]],"v":[[1.293,1.588],[0.92,1.821],[-1.596,2.677],[-3.863,2.377],[-4.531,1.106],[-3.231,-0.4],[-0.928,-1.813],[1.588,-2.667],[3.855,-2.367],[4.537,-1.099],[3.237,0.407],[2.864,0.64],[1.296,1.603]],"c":true},"ix":2},"nm":"Path 2","mn":"ADBE Vector Shape - Group","hd":false},{"ty":"fl","c":{"a":0,"k":[0.24,0.6453,1,1],"ix":4},"o":{"a":0,"k":100,"ix":5},"r":1,"bm":0,"nm":"Fill 1","mn":"ADBE Vector Graphic - Fill","hd":false},{"ty":"tr","p":{"a":0,"k":[133.015,-504.788],"ix":2},"a":{"a":0,"k":[0,0],"ix":1},"s":{"a":0,"k":[100,100],"ix":3},"r":{"a":0,"k":0,"ix":6},"o":{"a":0,"k":100,"ix":7},"sk":{"a":0,"k":0,"ix":4},"sa":{"a":0,"k":0,"ix":5},"nm":"Transform"}],"nm":"Path 2709-2","np":3,"cix":2,"bm":0,"ix":4,"mn":"ADBE Vector Group","hd":false}],"ip":3,"op":42,"st":3,"bm":0,"completed":true},{"ddd":1,"ind":8,"ty":4,"nm":"Layer 1","parent":6,"sr":1,"ks":{"o":{"a":1,"k":[{"i":{"x":[0.833],"y":[0.833]},"o":{"x":[0.167],"y":[0.167]},"t":9,"s":[0]},{"t":21,"s":[100]}],"ix":11},"rx":{"a":1,"k":[{"i":{"x":[0.42],"y":[1]},"o":{"x":[0.58],"y":[0]},"t":25,"s":[0]},{"t":55,"s":[178]}],"ix":8},"ry":{"a":0,"k":0,"ix":9},"rz":{"a":0,"k":0,"ix":10},"or":{"a":0,"k":[311,350,35],"ix":7},"p":{"a":1,"k":[{"i":{"x":0.833,"y":0.833},"o":{"x":0.167,"y":0.167},"t":25,"s":[24.375,-14.538,-32],"to":null,"ti":null},{"t":50,"s":[24.375,-14.538,-25]}],"ix":2},"a":{"a":0,"k":[0,60.303,0],"ix":1},"s":{"a":0,"k":[38,38,38],"ix":6}},"ao":0,"shapes":[{"ty":"gr","it":[{"ind":0,"ty":"sh","ix":1,"ks":{"a":0,"k":{"i":[[-120.353,60.303],[120.353,60.303],[-0.253,-60.303]],"o":[[-120.353,60.303],[120.353,60.303],[-0.253,-60.303]],"v":[[-120.353,60.303],[120.353,60.303],[-0.253,-60.303]],"c":true},"ix":2},"nm":"Path 1","mn":"ADBE Vector Shape - Group","hd":false,"_render":true},{"ty":"fl","c":{"a":0,"k":[0.88,0.88,0.88,1],"ix":4},"o":{"a":0,"k":100,"ix":5},"r":1,"bm":0,"nm":"Fill 1","mn":"ADBE Vector Graphic - Fill","hd":false,"_render":true},{"ty":"tr","p":{"a":0,"k":[0,0],"ix":2},"a":{"a":0,"k":[0,0],"ix":1},"s":{"a":0,"k":[100,100],"ix":3},"r":{"a":0,"k":0,"ix":6},"o":{"a":0,"k":100,"ix":7},"sk":{"a":0,"k":0,"ix":4},"sa":{"a":0,"k":0,"ix":5},"nm":"Transform","_render":true}],"nm":"Group 1","np":2,"cix":2,"bm":0,"ix":1,"mn":"ADBE Vector Group","hd":false,"_render":true}],"ip":-11,"op":50,"st":23,"bm":0,"completed":true},{"ddd":0,"ind":10,"ty":4,"nm":"Path 2716","sr":1,"ks":{"o":{"a":0,"k":20,"ix":11},"r":{"a":0,"k":0,"ix":10},"p":{"a":0,"k":[250,150,0],"ix":2},"a":{"a":0,"k":[0,0,0],"ix":1},"s":{"a":0,"k":[122.345,122.345,100],"ix":6}},"ao":0,"shapes":[{"ty":"gr","it":[{"ind":0,"ty":"sh","ix":1,"ks":{"a":0,"k":{"i":[[-13.15,-37.905],[-65.65,-7.595],[13.15,37.905],[65.65,7.572]],"o":[[-13.15,-37.905],[-65.65,-7.595],[13.15,37.905],[65.65,7.572]],"v":[[-13.15,-37.905],[-65.65,-7.595],[13.15,37.905],[65.65,7.572]],"c":true},"ix":2},"nm":"Path 1","mn":"ADBE Vector Shape - Group","hd":false},{"ty":"fl","c":{"a":0,"k":[0.97,0.97,0.97,1],"ix":4},"o":{"a":0,"k":100,"ix":5},"r":1,"bm":0,"nm":"Fill 1","mn":"ADBE Vector Graphic - Fill","hd":false},{"ty":"tr","p":{"a":0,"k":[0,0],"ix":2},"a":{"a":0,"k":[0,0],"ix":1},"s":{"a":0,"k":[100,100],"ix":3},"r":{"a":0,"k":0,"ix":6},"o":{"a":0,"k":100,"ix":7},"sk":{"a":0,"k":0,"ix":4},"sa":{"a":0,"k":0,"ix":5},"nm":"Transform"}],"nm":"Path 2716","np":2,"cix":2,"bm":0,"ix":1,"mn":"ADBE Vector Group","hd":false}],"ip":51.5,"op":72,"st":51.5,"bm":0,"completed":true},{"ddd":0,"ind":11,"ty":4,"nm":"Layer 2","sr":1,"ks":{"o":{"a":1,"k":[{"i":{"x":[0.833],"y":[0.833]},"o":{"x":[0.167],"y":[0.167]},"t":7,"s":[0]},{"i":{"x":[0.833],"y":[0.833]},"o":{"x":[0.167],"y":[0.167]},"t":23,"s":[100]},{"i":{"x":[0.833],"y":[0.833]},"o":{"x":[0.167],"y":[0.167]},"t":90,"s":[100]},{"t":108,"s":[0]}],"ix":11},"r":{"a":0,"k":0,"ix":10},"p":{"a":0,"k":[264.604,171.558,0],"ix":2},"a":{"a":0,"k":[0,0,0],"ix":1},"s":{"a":0,"k":[100,100,100],"ix":6}},"ao":0,"shapes":[{"ty":"gr","it":[{"ind":0,"ty":"sh","ix":1,"ks":{"a":0,"k":{"i":[[-205.486,4.442],[-30.65,110.622],[205.486,-42.646],[32.013,-110.622]],"o":[[-205.486,4.442],[-30.65,110.622],[205.486,-42.646],[32.013,-110.622]],"v":[[-205.486,4.442],[-30.65,110.622],[205.486,-42.646],[32.013,-110.622]],"c":true},"ix":2},"nm":"Path 1","mn":"ADBE Vector Shape - Group","hd":false,"_render":true},{"ty":"fl","c":{"a":0,"k":[0.9382,0.9401,0.9418,1],"ix":4},"o":{"a":0,"k":100,"ix":5},"r":1,"bm":0,"nm":"Fill 1","mn":"ADBE Vector Graphic - Fill","hd":false,"_render":true},{"ty":"tr","p":{"a":0,"k":[8.361,-5.232],"ix":2},"a":{"a":0,"k":[0,0],"ix":1},"s":{"a":0,"k":[58.317,58.317],"ix":3},"r":{"a":0,"k":0,"ix":6},"o":{"a":0,"k":100,"ix":7},"sk":{"a":0,"k":0,"ix":4},"sa":{"a":0,"k":0,"ix":5},"nm":"Transform","_render":true}],"nm":"Group 1","np":2,"cix":2,"bm":0,"ix":1,"mn":"ADBE Vector Group","hd":false,"_render":true}],"ip":0,"op":8268,"st":0,"bm":0,"completed":true},{"ddd":0,"ind":12,"ty":1,"nm":"BG","sr":1,"ks":{"o":{"a":0,"k":100,"ix":11},"r":{"a":0,"k":0,"ix":10},"p":{"a":0,"k":[250,150,0],"ix":2},"a":{"a":0,"k":[82,46,0],"ix":1},"s":{"a":0,"k":[326.829,326.829,100],"ix":6}},"ao":0,"sw":164,"sh":92,"sc":"#ffffff","ip":0,"op":781,"st":0,"bm":0,"completed":true}],"markers":[],"__complete":true}